http_to_xmpp.py
http_to_xmpp-0.2.dist-info/METADATA
http_to_xmpp-0.2.dist-info/WHEEL
http_to_xmpp-0.2.dist-info/entry_points.txt
http_to_xmpp-0.2.dist-info/top_level.txt
http_to_xmpp-0.2.dist-info/RECORD
