Metadata-Version: 2.1
Name: http-to-xmpp
Version: 0.2
Summary: Basic one way gate between HTTP and XMPP.
Author-email: Julien Palard <julien@palard.fr>
License: MIT License
Project-URL: homepage, https://git.afpy.org/mdk/http-to-xmpp
Requires-Python: >=3.7
Requires-Dist: aiohttp
Requires-Dist: aioxmpp
